codexl/__init__.py
codexl/cli.py
codexl/config.py
codexl/git_manager.py
codexl/iterm_manager.py
codexl-0.1.2.dist-info/METADATA
codexl-0.1.2.dist-info/WHEEL
codexl-0.1.2.dist-info/entry_points.txt
codexl-0.1.2.dist-info/top_level.txt
codexl-0.1.2.dist-info/RECORD
